README.md
setup.py
endoseg.egg-info/PKG-INFO
endoseg.egg-info/SOURCES.txt
endoseg.egg-info/dependency_links.txt
endoseg.egg-info/requires.txt
endoseg.egg-info/top_level.txt
src/__init__.py
src/endoseg.py
src/run.py