Metadata-Version: 1.0
Name: endoseg
Version: 0.2.0
Summary: Python module to segment the visible circular area of endoscopic images.
Home-page: https://github.com/luiscarlosgph/endoseg
Author: Luis C. Garcia-Peraza Herrera
Author-email: luiscarlos.gph@gmail.com
License: MIT License
Platform: UNKNOWN
